unicycle/__init__.py
unicycle/py.typed
unicycle/store.py
unicycle-0.0.1.dist-info/LICENSE
unicycle-0.0.1.dist-info/WHEEL
unicycle-0.0.1.dist-info/METADATA
unicycle-0.0.1.dist-info/RECORD
