Metadata-Version: 2.1
Name: unicycle
Version: 0.0.1
Summary: Predictable, unidirectional state store for Python.
Home-page: https://github.com/mcous/unicycle
License: MIT
Author: Mike Cousins
Author-email: mike@cousins.io
Requires-Python: >=3.7,<4.0
Classifier: Development Status :: 3 - Alpha
Classifier: Intended Audience :: Developers
Classifier: License :: OSI Approved :: MIT License
Classifier: Operating System :: OS Independent
Classifier: Programming Language :: Python :: 3
Classifier: Programming Language :: Python :: 3.10
Classifier: Programming Language :: Python :: 3.7
Classifier: Programming Language :: Python :: 3.8
Classifier: Programming Language :: Python :: 3.9
Classifier: Topic :: Utilities
Classifier: Typing :: Typed
Requires-Dist: anyio (>=3.5.0,<4.0.0)
Project-URL: Repository, https://github.com/mcous/unicycle
